{
  "SystemName": "Master",
  "PublicURL" : "https://dev.seq.moe/cds/files/",
  "LogServer" : [],
  "SQLServer" : "127.0.0.1",
  "MQServer"  : "127.0.0.1",
  "SQLUsername" : "eiga",
  "SQLPassword" : "",
  "SQLDatabase" : "kanmi_system",
  "MQUsername": "eiga",
  "MQPassword": "",
  "Flickr_Key": "",
  "Discord_Key": "",
  "Authware_Key": "",
  "Discord_In": "inbox.discord",
  "Discord_Out": "outbox.discord",
  "Twitter_In": "inbox.twitter",
  "Twitter_Out": "outbox.twitter",
  "Pixiv_In": "inbox.pixiv",
  "YouTube_In": "inbox.youtube",
  "YouTube_Out": "outbox.youtube",
  "Sequenzia_In": "inbox.sequenzia",
  "FileWorker_In": "inbox.fileworker",
  "DiscordHomeGuild": "",
  "Discord_Recycling_Bin": "",
  "DiscordUser": "2",
  "TwitterUser": "1",
  "PixivUser": "1",
  "YouTubeUser": "1",
  "RSSAccount": "1",
  "FlickrAccount": "1",
  "PickupFolder": "./../pickup/",
  "RadioFolder": "./../radio/",
  "WatchFolder_1": "./upload/",
  "WatchFolder_2": "null",
  "WatchFolder_3": "null",
  "TempFolder": "./temp",
  "ffmpeg_exec": "ffmpeg",
  "ffmpeg_vcodec": "h264",
  "ffmpeg_scale": "640:-1",
  "ffmpeg_vbitrate": "500K",
  "ffmpeg_vcrf": "30",
  "ffmpeg_acodec": "aac",
  "ffmpeg_abitrate": "128K",
  "Pixiv_NewIllust_Pull": "5",
  "Pixiv_Recomm_Pull": "60",
  "Twitter_Timeline_Pull": "1",
  "Twitter_Mention_Pull": "1",
  "Twitter_MediaUpload_Delay": "90",
  "Twitter_Interaction_Flow": "30",
  "FW_Accepted_Images": [ "jpg","png","jpeg","jiff","tiff", "gif", "webm" ],
  "FW_Always_Keep_Original_Images": false,
  "FW_Accepted_Videos": [ "mov","mp4","avi","mkv" ],
  "FW_Accepted_Files": [ "jpg","png","jpeg","jiff","tiff","mov","mp4","avi","mkv","zip","rar","tar","exe","unitypackage","txt","blend" ],
  "FW_Pickup_Enable": true,
  "Discord_Radio_Enable": false,
  "Discord_FSMgr_Enable": false
}